[
  {
    "id": "650686",
    "dateTime": "2026-04-04T02:30:00Z",
    "latitude": 71.3367,
    "longitude": 20.34,
    "heading": 313.0,
    "speed": 0.05144444444444445
  },
  {
    "id": "650686",
    "dateTime": "2026-04-04T03:00:00Z",
    "latitude": 71.3334,
    "longitude": 20.3555,
    "heading": 74.0,
    "speed": 0.15433333333333335
  },
  {
    "id": "650686",
    "dateTime": "2026-04-04T03:30:00Z",
    "latitude": 71.3333,
    "longitude": 20.3558,
    "heading": 45.0,
    "speed": 0.1028888888888889
  },
  {
    "id": "650686",
    "dateTime": "2026-04-04T04:00:00Z",
    "latitude": 71.3296,
    "longitude": 20.368100000000002,
    "heading": 182.0,
    "speed": 0.05144444444444445
  },
  {
    "id": "650686",
    "dateTime": "2026-04-04T08:30:00Z",
    "latitude": 71.2975,
    "longitude": 20.3695,
    "heading": 285.0,
    "speed": 0.15433333333333335
  },
  {
    "id": "650686",
    "dateTime": "2026-04-04T09:00:00Z",
    "latitude": 71.2952,
    "longitude": 20.3639,
    "heading": 102.0,
    "speed": 0.05144444444444445
  },
  {
    "id": "650686",
    "dateTime": "2026-04-04T09:30:00Z",
    "latitude": 71.2938,
    "longitude": 20.3603,
    "heading": 155.0,
    "speed": 0.0
  },
  {
    "id": "650686",
    "dateTime": "2026-04-04T10:00:00Z",
    "latitude": 71.2929,
    "longitude": 20.3583,
    "heading": 65.0,
    "speed": 0.1028888888888889
  }
]